proxypay/__init__.py
proxypay/admin.py
proxypay/api.py
proxypay/apps.py
proxypay/configs.py
proxypay/exceptions.py
proxypay/models.py
proxypay/signals.py
proxypay/utils.py
proxypay/views.py
proxypay/management/__init__.py
proxypay/management/commands/__init__.py
proxypay/management/commands/proxypay.py
proxypay/migrations/0001_initial.py
proxypay/migrations/0002_reference_expires_in.py
proxypay/migrations/0003_auto_20201025_2110.py
proxypay/migrations/0004_reference_paid_at.py
proxypay/migrations/0005_auto_20210108_1142.py
proxypay/migrations/0006_reference_key.py
proxypay/migrations/0007_auto_20210422_1744.py
proxypay/migrations/0008_auto_20210622_0841.py
proxypay/migrations/__init__.py
proxypay/references/__init__.py
proxypay/references/create.py
proxypay/references/get.py
django_proxypay-1.3.2.dist-info/LICENSE
django_proxypay-1.3.2.dist-info/METADATA
django_proxypay-1.3.2.dist-info/WHEEL
django_proxypay-1.3.2.dist-info/top_level.txt
django_proxypay-1.3.2.dist-info/RECORD
