Metadata-Version: 2.1
Name: django-proxypay
Version: 1.3.2
Summary: Django Proxypay is a Django Framework application/library that facilitates the integration of your Django project with theProxypay API. Allowing to generate referrals, recognize payments and look through Proxypay's webhooks
Home-page: https://github.com/txiocoder/django-proxypay
Author: Ageu Matheus
Author-email: txiocoder@gmail.com
Maintainer: Ageu Matheus
Maintainer-email: txiocoder@gmail.com
License: MIT License
Project-URL: Changelog, https://github.com/txiocoder/django-proxypay/blob/master/HISTORY.md
Keywords: django,payments,proxypay,django-proxypay
Platform: UNKNOWN
Classifier: Environment :: Web Environment
Classifier: Framework :: Django
Classifier: Intended Audience :: Developers
Classifier: License :: OSI Approved :: MIT License
Classifier: Operating System :: OS Independent
Classifier: Programming Language :: Python
Classifier: Programming Language :: Python :: 3
Classifier: Topic :: Software Development :: Libraries :: Application Frameworks
Classifier: Topic :: Software Development :: Libraries :: Python Modules
Requires-Python: >=3.8
License-File: LICENSE
Requires-Dist: Django (>=3)
Requires-Dist: requests (>=2)
Requires-Dist: django-admin-display
